dbengine-1.1.0.dist-info/METADATA
dbengine-1.1.0.dist-info/WHEEL
dbengine-1.1.0.dist-info/entry_points.txt
dbengine-1.1.0.dist-info/licenses/LICENSE
dbengine/__init__.py
dbengine/core/__init__.py
dbengine/core/config.py
dbengine/core/database.py
dbengine/core/exceptions.py
dbengine/core/filter_operators.py
dbengine/engines/__init__.py
dbengine/engines/parquet.py
dbengine/engines/postgresql.py
dbengine/engines/sqlite.py
dbengine/services/__init__.py
dbengine/services/config_factory.py
dbengine/services/database_factory.py
dbengine/utils/__init__.py
dbengine/utils/logging.py
dbengine/utils/postgres_server.py
dbengine-1.1.0.dist-info/RECORD
