Metadata-Version: 2.1
Name: dbengine
Version: 1.1.0
Summary: A Python package providing a unified interface for database operations, supporting Parquet, SQLite, and PostgreSQL backends.
Author-Email: Tome Magalhaes Gouveia <tome.pmg@gmail.com>
Classifier: Programming Language :: Python :: 3
Classifier: Operating System :: OS Independent
Requires-Dist: pandas>=2.0.0
Requires-Dist: pyyaml>=6.0
Requires-Dist: psycopg2-binary>=2.9.0
Requires-Dist: pyarrow>=12.0.0
Requires-Dist: sqlalchemy~=2.0.43
Provides-Extra: dev
Requires-Dist: black; extra == "dev"
Requires-Dist: flake8; extra == "dev"
Requires-Dist: isort; extra == "dev"
Requires-Dist: ipykernel; extra == "dev"
Requires-Dist: pre-commit; extra == "dev"
Requires-Dist: pytest>=7.0.0; extra == "dev"
Requires-Dist: pytest-cov>=4.0.0; extra == "dev"
